{
    "phrase":
    {
        "subject":[
            {
            "Generate":[
                "americanForenames", 
                "dutchForenames", 
                "frenchForenames", 
                "germanForenames", 
                "iselandicForenames", 
                "indianForenames", 
                "irishForenames", 
                "italianForenames", 
                "japaneseForenames", 
                "russianForenames", 
                "spanishForenames", 
                "swedishForenames"]
            }
        ],
        "predicate":[
            {
                "Choose":[
                    "get",
                    "acquire"]
            }
        ],
        "objekt":[
            {
                "Generate":[
                    "americanCities", 
                    "capitolCities", 
                    "greekIslands", 
                    "japaneseCities", 
                    "italianCities", 
                    "fellsInCambria", 
                    "germanTowns", 
                    "countries", 
                    "englishTowns", 
                    "placesInCumbria", 
                    "supermarketsAndDiscountStores", 
                    "swissCities", 
                    "russianCities", 
                    "chineseCities", 
                    "romanPlacesNames"]
            }
        ],
        "complements":[
            {
                "Word":"from"
            },
            {
            "Generate":[
                "americanCities", 
                "capitolCities", 
                "greekIslands", 
                "japaneseCities", 
                "italianCities", 
                "fellsInCambria", 
                "germanTowns", 
                "countries", 
                "englishTowns", 
                "placesInCumbria", 
                "supermarketsAndDiscountStores", 
                "swissCities", 
                "russianCities", 
                "chineseCities", 
                "romanPlacesNames"]
            }
        ]
    },
    "features":{
        "tense":"FUTURE"
    }
}